{
    "function_method_name": "extract_markdown_to_file_from_any_document_complex",
    "num_pages": 74,
    "time_start_1": 1763098157.484224,
    "time_end_1": 1763098171.531664,
    "time_total_1": 14.047439813613892,
    "pages_per_second_1": 5.267863823006658,
    "time_start_2": 64367.99645225,
    "time_end_2": 64382.043783791,
    "time_total_2": 14.04733154099813,
    "pages_per_second_2": 5.2679044261200625,
    "time_start_3": 64367996452291,
    "time_end_3": 64382043783958,
    "time_total_3": 14.047331667,
    "pages_per_second_3": 5.26790437886797
}