{
    "function_method_name": "extract_markdown_to_file_from_any_document",
    "num_pages": 111,
    "time_start_1": 1763094332.426481,
    "time_end_1": 1763094353.529537,
    "time_total_1": 21.103055953979492,
    "pages_per_second_1": 5.259901705329472,
    "time_start_2": 60542.992265375,
    "time_end_2": 60564.095329333,
    "time_total_2": 21.10306395799853,
    "pages_per_second_2": 5.259899710341755,
    "time_start_3": 60542992265416,
    "time_end_3": 60564095329541,
    "time_total_3": 21.103064125,
    "pages_per_second_3": 5.2598996687169475
}