{
    "function_method_name": "extract_markdown_to_file_from_any_document_complex",
    "num_pages": 350,
    "time_start_1": 1763185286.596389,
    "time_end_1": 1763185367.190945,
    "time_total_1": 80.59455585479736,
    "pages_per_second_1": 4.342725092133706,
    "time_start_2": 151496.880688916,
    "time_end_2": 151577.474653416,
    "time_total_2": 80.5939645000035,
    "pages_per_second_2": 4.3427569566947515,
    "time_start_3": 151496880689083,
    "time_end_3": 151577474653708,
    "time_total_3": 80.593964625,
    "pages_per_second_3": 4.342756949959391
}