{
    "function_method_name": "extract_markdown_to_file_from_any_document",
    "num_pages": 106,
    "time_start_1": 1763096058.256536,
    "time_end_1": 1763096081.214606,
    "time_total_1": 22.958070039749146,
    "pages_per_second_1": 4.617112841648872,
    "time_start_2": 62268.820767125,
    "time_end_2": 62291.778838958,
    "time_total_2": 22.958071833003487,
    "pages_per_second_2": 4.617112481006318,
    "time_start_3": 62268820767166,
    "time_end_3": 62291778839041,
    "time_total_3": 22.958071875,
    "pages_per_second_3": 4.617112472560373
}