{
    "function_method_name": "extract_markdown_to_file_from_any_document",
    "num_pages": 193,
    "time_start_1": 1763193149.708819,
    "time_end_1": 1763193202.441092,
    "time_total_1": 52.73227310180664,
    "pages_per_second_1": 3.659997732837876,
    "time_start_2": 159360.0346925,
    "time_end_2": 159412.767034041,
    "time_total_2": 52.73234154100646,
    "pages_per_second_2": 3.6599929826730078,
    "time_start_3": 159360034692708,
    "time_end_3": 159412767034208,
    "time_total_3": 52.7323415,
    "pages_per_second_3": 3.659992985519143
}