{
    "function_method_name": "extract_markdown_to_file_from_any_document_complex",
    "num_pages": 0,
    "time_start_1": 1771403008.860778,
    "time_end_1": 1771403024.3225338,
    "time_total_1": 15.461755752563477,
    "pages_per_second_1": 0.0,
    "time_start_2": 409997.684148583,
    "time_end_2": 410013.14586175,
    "time_total_2": 15.461713167023845,
    "pages_per_second_2": 0.0,
    "time_start_3": 409997684148708,
    "time_end_3": 410013145864958,
    "time_total_3": 15.46171625,
    "pages_per_second_3": 0.0
}