{
    "function_method_name": "extract_markdown_to_file_from_any_document_complex",
    "num_pages": 100,
    "time_start_1": 1763115693.706532,
    "time_end_1": 1763115712.5421891,
    "time_total_1": 18.835657119750977,
    "pages_per_second_1": 5.30907944247618,
    "time_start_2": 81904.199902041,
    "time_end_2": 81923.035423416,
    "time_total_2": 18.835521375003736,
    "pages_per_second_2": 5.309117704206909,
    "time_start_3": 81904199902125,
    "time_end_3": 81923035423583,
    "time_total_3": 18.835521458,
    "pages_per_second_3": 5.309117680812976
}