{
    "function_method_name": "extract_markdown_to_file_from_any_document",
    "num_pages": 31,
    "time_start_1": 1763199774.86961,
    "time_end_1": 1763199780.792471,
    "time_total_1": 5.922860860824585,
    "pages_per_second_1": 5.233957158278433,
    "time_start_2": 165985.164221625,
    "time_end_2": 165991.087080958,
    "time_total_2": 5.922859333019005,
    "pages_per_second_2": 5.23395850838123,
    "time_start_3": 165985164221833,
    "time_end_3": 165991087081083,
    "time_total_3": 5.92285925,
    "pages_per_second_3": 5.233958581744113
}