{
    "function_method_name": "extract_markdown_to_file_from_any_document",
    "num_pages": 31,
    "time_start_1": 1763109632.169149,
    "time_end_1": 1763109638.3999171,
    "time_total_1": 6.230768203735352,
    "pages_per_second_1": 4.975309462068493,
    "time_start_2": 75842.649958125,
    "time_end_2": 75848.8806975,
    "time_total_2": 6.230739375008852,
    "pages_per_second_2": 4.97533248210305,
    "time_start_3": 75842649958208,
    "time_end_3": 75848880697625,
    "time_total_3": 6.230739417,
    "pages_per_second_3": 4.975332448572532
}