{
    "function_method_name": "extract_markdown_to_file_from_any_document",
    "num_pages": 31,
    "time_start_1": 1772651840.557201,
    "time_end_1": 1772651847.037875,
    "time_total_1": 6.4806740283966064,
    "pages_per_second_1": 4.783453058148916,
    "time_start_2": 839570.969768375,
    "time_end_2": 839577.450419,
    "time_total_2": 6.480650624958798,
    "pages_per_second_2": 4.783470332532714,
    "time_start_3": 839570969768458,
    "time_end_3": 839577450419208,
    "time_total_3": 6.48065075,
    "pages_per_second_3": 4.783470240237834
}