{
    "function_method_name": "extract_markdown_to_file_from_any_document",
    "num_pages": 2,
    "time_start_1": 1763102219.348381,
    "time_end_1": 1763102222.880922,
    "time_total_1": 3.532541036605835,
    "pages_per_second_1": 0.5661646897445971,
    "time_start_2": 68429.885007,
    "time_end_2": 68433.4175485,
    "time_total_2": 3.5325414999970235,
    "pages_per_second_2": 0.566164615476332,
    "time_start_3": 68429885007041,
    "time_end_3": 68433417548708,
    "time_total_3": 3.532541667,
    "pages_per_second_3": 0.5661645887105682
}