{
    "function_method_name": "extract_markdown_to_file_from_any_document",
    "num_pages": 2,
    "time_start_1": 1763197427.148104,
    "time_end_1": 1763197430.263534,
    "time_total_1": 3.1154301166534424,
    "pages_per_second_1": 0.6419659325077001,
    "time_start_2": 163637.410449833,
    "time_end_2": 163640.525849916,
    "time_total_2": 3.11540008301381,
    "pages_per_second_2": 0.6419721213030263,
    "time_start_3": 163637410449875,
    "time_end_3": 163640525850000,
    "time_total_3": 3.115400125,
    "pages_per_second_3": 0.6419721126511799
}