{
    "function_method_name": "extract_markdown_to_file_from_any_document",
    "num_pages": 0,
    "time_start_1": 1763156887.783801,
    "time_end_1": 1763156889.000018,
    "time_total_1": 1.216216802597046,
    "pages_per_second_1": 0.0,
    "time_start_2": 123098.183186875,
    "time_end_2": 123099.399403666,
    "time_total_2": 1.2162167909991695,
    "pages_per_second_2": 0.0,
    "time_start_3": 123098183186958,
    "time_end_3": 123099399403750,
    "time_total_3": 1.216216792,
    "pages_per_second_3": 0.0
}