{
    "function_method_name": "extract_markdown_to_file_from_any_document_complex",
    "num_pages": 174,
    "time_start_1": 1763224309.610771,
    "time_end_1": 1763224338.907878,
    "time_total_1": 29.297106981277466,
    "pages_per_second_1": 5.9391529720390475,
    "time_start_2": 190519.832688291,
    "time_end_2": 190549.129899958,
    "time_total_2": 29.29721166699892,
    "pages_per_second_2": 5.939131750070187,
    "time_start_3": 190519832688333,
    "time_end_3": 190549129900083,
    "time_total_3": 29.29721175,
    "pages_per_second_3": 5.9391317332442055
}