{
    "function_method_name": "extract_markdown_to_file_from_any_document_complex",
    "num_pages": 19,
    "time_start_1": 1763073412.26176,
    "time_end_1": 1763073429.848704,
    "time_total_1": 17.586944103240967,
    "pages_per_second_1": 1.0803468691583906,
    "time_start_2": 39622.76645925,
    "time_end_2": 39640.353279791,
    "time_total_2": 17.586820541000634,
    "pages_per_second_2": 1.0803544595059,
    "time_start_3": 39622766459333,
    "time_end_3": 39640353280000,
    "time_total_3": 17.586820667,
    "pages_per_second_3": 1.080354451765787
}