{
    "function_method_name": "extract_markdown_to_file_from_any_document_complex",
    "num_pages": 19,
    "time_start_1": 1763189920.793505,
    "time_end_1": 1763189938.706657,
    "time_total_1": 17.91315197944641,
    "pages_per_second_1": 1.0606731870416017,
    "time_start_2": 156131.1117435,
    "time_end_2": 156149.024896583,
    "time_total_2": 17.913153083005454,
    "pages_per_second_2": 1.0606731216976903,
    "time_start_3": 156131111743583,
    "time_end_3": 156149024896708,
    "time_total_3": 17.913153125,
    "pages_per_second_3": 1.0606731192111103
}