{
    "function_method_name": "extract_markdown_to_file_from_any_document",
    "num_pages": 3,
    "time_start_1": 1763065907.067399,
    "time_end_1": 1763065908.8953469,
    "time_total_1": 1.8279478549957275,
    "pages_per_second_1": 1.6411846715436047,
    "time_start_2": 32117.664827541,
    "time_end_2": 32119.492783416,
    "time_total_2": 1.8279558750000433,
    "pages_per_second_2": 1.6411774709824047,
    "time_start_3": 32117664827583,
    "time_end_3": 32119492783500,
    "time_total_3": 1.827955917,
    "pages_per_second_3": 1.6411774332739557
}