{
  "function_method_name": "extract_markdown_to_file_from_any_document",
  "num_pages": 0,
  "time_start_1": 1773005151.084358,
  "time_end_1": 1773005151.170934,
  "time_total_1": 0.08657598495483398,
  "pages_per_second_1": 0.0,
  "time_start_2": 1164803.600783875,
  "time_end_2": 1164803.687360041,
  "time_total_2": 0.08657616609707475,
  "pages_per_second_2": 0.0,
  "time_start_3": 1164803600783916,
  "time_end_3": 1164803687360166,
  "time_total_3": 0.08657625,
  "pages_per_second_3": 0.0
}