{
    "function_method_name": "extract_markdown_to_file_from_any_document",
    "num_pages": 48,
    "time_start_1": 1763187235.6358662,
    "time_end_1": 1763187277.309643,
    "time_total_1": 41.67377686500549,
    "pages_per_second_1": 1.1518034507764232,
    "time_start_2": 153445.962655791,
    "time_end_2": 153487.636585,
    "time_total_2": 41.67392920900602,
    "pages_per_second_2": 1.151799240222035,
    "time_start_3": 153445962655833,
    "time_end_3": 153487636585125,
    "time_total_3": 41.673929292,
    "pages_per_second_3": 1.1517992379282171
}