{
    "function_method_name": "extract_markdown_to_file_from_any_document_complex",
    "num_pages": 48,
    "time_start_1": 1763199725.5576751,
    "time_end_1": 1763199768.5392761,
    "time_total_1": 42.98160099983215,
    "pages_per_second_1": 1.1167569118746286,
    "time_start_2": 165935.852307875,
    "time_end_2": 165978.833890541,
    "time_total_2": 42.98158266599057,
    "pages_per_second_2": 1.1167573882285233,
    "time_start_3": 165935852307958,
    "time_end_3": 165978833890583,
    "time_total_3": 42.981582625,
    "pages_per_second_3": 1.1167573892935498
}