{
    "function_method_name": "extract_markdown_to_file_from_any_document_complex",
    "num_pages": 232,
    "time_start_1": 1763178030.778143,
    "time_end_1": 1763178077.064706,
    "time_total_1": 46.28656315803528,
    "pages_per_second_1": 5.012253755110033,
    "time_start_2": 144241.151644791,
    "time_end_2": 144287.438084375,
    "time_total_2": 46.286439583986066,
    "pages_per_second_2": 5.012267136664064,
    "time_start_3": 144241151644875,
    "time_end_3": 144287438084500,
    "time_total_3": 46.286439625,
    "pages_per_second_3": 5.012267132222745
}