{
    "function_method_name": "extract_markdown_to_file_from_any_document_complex",
    "num_pages": 104,
    "time_start_1": 1763138414.428888,
    "time_end_1": 1763138447.2655308,
    "time_total_1": 32.83664274215698,
    "pages_per_second_1": 3.1671934556963914,
    "time_start_2": 104624.838447041,
    "time_end_2": 104657.690634833,
    "time_total_2": 32.85218779199931,
    "pages_per_second_2": 3.165694798120195,
    "time_start_3": 104624838447458,
    "time_end_3": 104657690635000,
    "time_total_3": 32.852187542,
    "pages_per_second_3": 3.16569482221057
}