{
    "function_method_name": "extract_markdown_to_file_from_any_document",
    "num_pages": 31,
    "time_start_1": 1763230897.953214,
    "time_end_1": 1763230902.286198,
    "time_total_1": 4.33298397064209,
    "pages_per_second_1": 7.154422958875202,
    "time_start_2": 197108.151935541,
    "time_end_2": 197112.48490925,
    "time_total_2": 4.332973708980717,
    "pages_per_second_2": 7.154439902496524,
    "time_start_3": 197108151935666,
    "time_end_3": 197112484909291,
    "time_total_3": 4.332973625,
    "pages_per_second_3": 7.154440041162263
}