{
    "function_method_name": "extract_markdown_to_file_from_any_document",
    "num_pages": 43,
    "time_start_1": 1763231755.9076622,
    "time_end_1": 1763231762.433511,
    "time_total_1": 6.525848865509033,
    "pages_per_second_1": 6.589181099070073,
    "time_start_2": 197966.109337083,
    "time_end_2": 197972.635176375,
    "time_total_2": 6.525839292007731,
    "pages_per_second_2": 6.589190765494728,
    "time_start_3": 197966109337125,
    "time_end_3": 197972635176458,
    "time_total_3": 6.525839333,
    "pages_per_second_3": 6.589190724104515
}