{
    "function_method_name": "extract_markdown_to_file_from_any_document",
    "num_pages": 43,
    "time_start_1": 1763206063.240242,
    "time_end_1": 1763206072.107681,
    "time_total_1": 8.867439031600952,
    "pages_per_second_1": 4.849201651881745,
    "time_start_2": 172273.531983083,
    "time_end_2": 172282.399409875,
    "time_total_2": 8.867426792014157,
    "pages_per_second_2": 4.849208345167847,
    "time_start_3": 172273531983166,
    "time_end_3": 172282399410041,
    "time_total_3": 8.867426875,
    "pages_per_second_3": 4.849208299786516
}