{
    "function_method_name": "extract_markdown_to_file_from_any_document_complex",
    "num_pages": 70,
    "time_start_1": 1763186393.267873,
    "time_end_1": 1763186414.3919628,
    "time_total_1": 21.12408971786499,
    "pages_per_second_1": 3.313752257963563,
    "time_start_2": 152603.547578291,
    "time_end_2": 152624.671518125,
    "time_total_2": 21.12393983398215,
    "pages_per_second_2": 3.3137757705307784,
    "time_start_3": 152603547578375,
    "time_end_3": 152624671518291,
    "time_total_3": 21.123939916,
    "pages_per_second_3": 3.3137757576643923
}