{
    "function_method_name": "extract_markdown_to_file_from_any_document",
    "num_pages": 70,
    "time_start_1": 1763123759.3381162,
    "time_end_1": 1763123781.102088,
    "time_total_1": 21.76397180557251,
    "pages_per_second_1": 3.2163246959397824,
    "time_start_2": 89969.807718625,
    "time_end_2": 89991.571729375,
    "time_total_2": 21.764010750004672,
    "pages_per_second_2": 3.2163189406614756,
    "time_start_3": 89969807718666,
    "time_end_3": 89991571729541,
    "time_total_3": 21.764010875,
    "pages_per_second_3": 3.2163189221894743
}