{
    "function_method_name": "extract_markdown_to_file_from_any_document",
    "num_pages": 70,
    "time_start_1": 1763196376.41052,
    "time_end_1": 1763196398.007463,
    "time_total_1": 21.596942901611328,
    "pages_per_second_1": 3.2411994752635738,
    "time_start_2": 162586.683149,
    "time_end_2": 162608.279881041,
    "time_total_2": 21.59673204101273,
    "pages_per_second_2": 3.241231120850519,
    "time_start_3": 162586683149166,
    "time_end_3": 162608279881208,
    "time_total_3": 21.596732042,
    "pages_per_second_3": 3.2412311207023494
}