{
    "function_method_name": "extract_markdown_to_file_from_any_document_complex",
    "num_pages": 40,
    "time_start_1": 1763129994.336111,
    "time_end_1": 1763130006.481625,
    "time_total_1": 12.145514011383057,
    "pages_per_second_1": 3.2933970486972455,
    "time_start_2": 96204.713038666,
    "time_end_2": 96216.858436958,
    "time_total_2": 12.145398292006576,
    "pages_per_second_2": 3.293428427647842,
    "time_start_3": 96204713038708,
    "time_end_3": 96216858437041,
    "time_total_3": 12.145398333,
    "pages_per_second_3": 3.2934284165317878
}