{
    "function_method_name": "extract_markdown_to_file_from_any_document_complex",
    "num_pages": 40,
    "time_start_1": 1763061089.10886,
    "time_end_1": 1763061101.617543,
    "time_total_1": 12.5086829662323,
    "pages_per_second_1": 3.1977787036398344,
    "time_start_2": 27299.710805333,
    "time_end_2": 27312.21954,
    "time_total_2": 12.508734666997043,
    "pages_per_second_2": 3.197765486667146,
    "time_start_3": 27299710805375,
    "time_end_3": 27312219540125,
    "time_total_3": 12.50873475,
    "pages_per_second_3": 3.1977654654480543
}